{
  "users": [
    {
      "name": "demo",
      "email": "demo@demo",
      "password": "demo",
      "id": "1"
    },
    {
      "name": "Инесса",
      "email": "inessa.shuvalova@mail.ru",
      "password": "iloverussia282828",
      "id": "rsmdv7o8ko3u4jx5"
    },
    {
      "name": "",
      "email": "",
      "password": "",
      "id": "rsmdv5c8koilmz9n"
    }
  ],
  "accounts": [
    {
      "name": "Банк",
      "user_id": "1",
      "id": "1"
    },
    {
      "name": "Магазин",
      "user_id": "1",
      "id": "2"
    },
    {
      "name": "Бизнес",
      "user_id": "1",
      "id": "3"
    },
    {
      "name": "",
      "user_id": "rsmdv7o8ko3u4jx5",
      "id": "rsmdv9n4koilmdnb"
    },
    {
      "name": "Сбербанк",
      "user_id": "rsmdv5c8koilmz9n",
      "id": "rsmdvawckozit4t1"
    },
    {
      "name": "сбербанк",
      "user_id": "rsmdv5c8koilmz9n",
      "id": "rsmdvam8koziuvc8"
    }
  ],
  "transactions": [
    {
      "account_id": "1",
      "created_at": "2019-09-15 10:24:02",
      "id": "1",
      "name": "Кредит",
      "sum": 5000,
      "type": "expense",
      "user_id": "1"
    },
    {
      "account_id": "1",
      "created_at": "2019-09-17 15:53:02",
      "id": "2",
      "name": "Баланс на дебетовке",
      "sum": 3200,
      "type": "income",
      "user_id": "1"
    },
    {
      "account_id": "1",
      "created_at": "2019-09-19 20:12:02",
      "id": "3",
      "name": "Копилка",
      "sum": 1500,
      "type": "income",
      "user_id": "1"
    },
    {
      "account_id": "2",
      "created_at": "2019-09-26 16:23:02",
      "id": "4",
      "name": "Молочные продукты",
      "sum": 100,
      "type": "income",
      "user_id": "1"
    },
    {
      "account_id": "2",
      "created_at": "2019-09-25 15:03:02",
      "id": "5",
      "name": "Фрукты",
      "sum": 250,
      "type": "income",
      "user_id": "1"
    },
    {
      "account_id": "2",
      "created_at": "2019-09-25 15:03:02",
      "id": "17",
      "name": "Овощи",
      "sum": 300,
      "type": "income",
      "user_id": "1"
    },
    {
      "account_id": "2",
      "created_at": "2019-09-26 14:47:02",
      "id": "6",
      "name": "Мясо",
      "sum": 600,
      "type": "income",
      "user_id": "1"
    },
    {
      "account_id": "2",
      "created_at": "2019-09-27 13:27:02",
      "id": "7",
      "name": "Долг в банк",
      "sum": 5000,
      "type": "expense",
      "user_id": "1"
    },
    {
      "account_id": "3",
      "created_at": "2017-10-15 13:27:02",
      "id": "9",
      "name": "На банду",
      "sum": 15000,
      "type": "expense",
      "user_id": "1"
    },
    {
      "account_id": "3",
      "created_at": "2017-09-17 13:27:02",
      "id": "10",
      "name": "На стволы",
      "sum": 6000,
      "type": "expense",
      "user_id": "1"
    },
    {
      "account_id": "3",
      "created_at": "2017-12-27 13:27:02",
      "id": "11",
      "name": "Прибыль с банка",
      "sum": 1500000,
      "type": "income",
      "user_id": "1"
    },
    {
      "account_id": "3",
      "created_at": "2018-01-15 13:27:02",
      "id": "12",
      "name": "Прибыль с магазина",
      "sum": 300000,
      "type": "income",
      "user_id": "1"
    },
    {
      "account_id": "3",
      "created_at": "2018-01-15 13:27:02",
      "id": "13",
      "name": "Подарок сизого",
      "sum": 20000,
      "type": "income",
      "user_id": "1"
    },
    {
      "account_id": "3",
      "created_at": "2017-09-15 13:27:02",
      "id": "14",
      "name": "На охрану",
      "sum": 60000,
      "type": "expense",
      "user_id": "1"
    },
    {
      "account_id": "3",
      "created_at": "2017-10-15 13:27:02",
      "id": "15",
      "name": "На бумер",
      "sum": 300000,
      "type": "expense",
      "user_id": "1"
    },
    {
      "id": "rsmdv2sgkozisrwv",
      "type": "income",
      "name": "услуги",
      "sum": 200,
      "account_id": "rsmdv9n4koilmdnb",
      "user_id": "rsmdv7o8ko3u4jx5",
      "created_at": "2021-05-22T08:59:09.774Z"
    },
    {
      "id": "rsmdvc20kozkew71",
      "type": "income",
      "name": "оказание услуг",
      "sum": 5000,
      "account_id": "rsmdv9n4koilmdnb",
      "user_id": "rsmdv7o8ko3u4jx5",
      "created_at": "2021-05-22T09:44:21.372Z"
    },
    {
      "id": "rsmdvc00kp0pgh3m",
      "type": "income",
      "name": "услуги",
      "sum": 1000,
      "user_id": "rsmdv7o8ko3u4jx5",
      "created_at": "2021-05-23T04:53:19.377Z"
    },
    {
      "id": "rsmdv5f0kp0ps3k9",
      "type": "income",
      "name": "услуги",
      "sum": 9000,
      "user_id": "rsmdv5c8koilmz9n",
      "created_at": "2021-05-23T05:02:21.704Z"
    },
    {
      "id": "rsmdv5askp1l4bvw",
      "type": "income",
      "name": "услуги",
      "sum": 9000,
      "user_id": "rsmdv5c8koilmz9n",
      "created_at": "2021-05-23T19:39:40.459Z"
    }
  ]
}